{
  "manifest_version": "1.0",
  "batch_id": "2026-03-31_batch_02",
  "date": "2026-03-31",
  "documents_analyzed": [
    "2000-08-22_[329]_l_warrantydeed_surface+minerals_gbdorsetttrust_cstiblieretal.md"
  ],
  "batch_summary": "Deed [329] — Warranty Deed with Vendor's Lien, Genevieve B. Dorsett Family Trust (Donald J. Dorsett, Trustee) → Cynthia S. Tiblier and husband Bruce V. Tiblier; 0.326 ac in Block 22, City of Tehuacana, Limestone County; $10 + $76,000 vendor's lien (Cendant Mortgage Corporation); executed 08/22/2000, filed 08/25/2000, recorded 08/28/2000; LC Vol. 1040 Pg. 510–512, Inst# 00003589. NON-PROJECT PROPERTY — completes the Dorsett Family Trust real property disposition chain (Genevieve → Trust [325] 1993 → Tiblier [329] 2000). ISSUE-43 item 15 marked PULLED. All Dorsett real property in Limestone County now fully accounted for.",
  "files": {
    "01_FAMILY_ENTITY_STRUCTURE.md": {
      "changed": true,
      "timestamp_summary": "Deed [329] — Dorsett Family Trust post-death disposition confirmed (Warranty Deed with Vendor's Lien → Tiblier, 0.326 ac Block 22 Tehuacana, $76,000); NON-PROJECT PROPERTY; all Dorsett LC real property fully traced",
      "operations": [
        {
          "action": "replace",
          "description": "Update Genevieve Dorsett entry: replace brief index reference to trust→Tiblier disposition with confirmed deed [329] details (second occurrence, near end of entry)",
          "find": "The trust disposed of its property post-death to Tiblier (Inst# 00003589, 08/25/2000).",
          "replace_with": "The trust disposed of its sole real property to Tiblier via deed [329] (Warranty Deed with Vendor's Lien, 08/22/2000, LC Vol. 1040, Pg. 510–512, Inst# 00003589; PDF CONFIRMED 2026-03-31)."
        },
        {
          "action": "replace",
          "description": "Update Genevieve Dorsett entry: replace brief index reference to trust→Tiblier disposition with confirmed deed [329] details (first occurrence, in trust history paragraph)",
          "find": "Trust conveyed property post-death (Inst# 00003589, 08/25/2000, DORSETT GENEVIEVE B FAMILY TRUST → Tiblier).",
          "replace_with": "**Deed [329] (PDF CONFIRMED 2026-03-31)**: Warranty Deed with Vendor's Lien, Genevieve B. Dorsett Family Trust (Donald J. Dorsett, Trustee) → Cynthia S. Tiblier and husband Bruce V. Tiblier (Navarro County TX). 0.326 ac in Block 22, City of Tehuacana (= same 100×137 ft lot from deed [325]; source deed cross-referenced as Vol. 890 Pg. 270 confirming [325] chain). Consideration: $10.00 + $76,000 vendor's lien (Cendant Mortgage Corporation). Subject to \"all minerals and royalty reservations and conveyances of record\" (boilerplate — no actual reservation by trust; deed [325] conveyed full fee simple including minerals). Grantees' address: P.O. Box 191, Tehuacana TX 76686. Acknowledged Aug 22, 2000 before Benjie Reed NP, Limestone County (comm. exp. 9/26/2000). Attorney: Reed & Reed L.L.P., P.O. Box 1072, Mexia TX 76667. LC Vol. 1040, Pg. 510–512, Inst# 00003589, Doc# 003589. Filed Aug 25, 2000 4:21 PM; recorded Aug 28, 2000 4:00 PM; Sue Lown, County Clerk. NON-PROJECT PROPERTY — completes Dorsett Family Trust real property disposition chain: Genevieve → Trust ([325], 1993) → Tiblier ([329], 2000). **All Dorsett Limestone County real property now fully accounted for**: Block 23 lot sold to Eady ([310], 1959); Block 22 lot conveyed to trust ([325], 1993), then sold by trust to Tiblier ([329], 2000); Boyd Survey sold to Simmons ([318], 1975). Estate had no real property at death ([328], 1999)."
        }
      ]
    },
    "02_PROPERTY_INVENTORY.md": {
      "changed": false,
      "timestamp_summary": null,
      "operations": []
    },
    "03_DEED_CHAIN_SUMMARY.md": {
      "changed": false,
      "timestamp_summary": null,
      "operations": []
    },
    "04_MINERAL_RIGHTS_TRACKER.md": {
      "changed": false,
      "timestamp_summary": null,
      "operations": []
    },
    "05_OPEN_ISSUES.md": {
      "changed": true,
      "timestamp_summary": "Deed [329] — ISSUE-43 item 15 marked PULLED (Dorsett Family Trust → Tiblier, 0.326 ac Block 22 Tehuacana); NON-PROJECT PROPERTY; all ISSUE-01 Dorsett pull list items now complete",
      "operations": [
        {
          "action": "replace",
          "description": "Update ISSUE-01 revised priority pull list item 5 to mark deed [329] as PULLED",
          "find": "(5) LC Inst# 00003589, Vol. 1040, Pg. 510 — Dorsett Family Trust → Tiblier;",
          "replace_with": "(5) ~~LC Inst# 00003589, Vol. 1040, Pg. 510~~ — **PULLED ✓ = deed [329]**; Warranty Deed with Vendor's Lien, Dorsett Family Trust (Donald J. Dorsett, Trustee) → Cynthia S. Tiblier + Bruce V. Tiblier; 0.326 ac Block 22 City of Tehuacana; $10 + $76,000 vendor's lien (Cendant Mortgage); NON-PROJECT PROPERTY — completes trust disposition chain;"
        },
        {
          "action": "replace",
          "description": "Update ISSUE-01 Dorsett family identified bullet (d) to note deed [329] is now confirmed",
          "find": "DORSETT GENEVIEVE B FAMILY TRUST existed and conveyed property post-death (Inst# 00003589, Vol. 1040, Pg. 510, 08/25/2000).",
          "replace_with": "DORSETT GENEVIEVE B FAMILY TRUST existed and conveyed property post-death — **PULLED ✓ = deed [329]** (Warranty Deed with Vendor's Lien, Donald J. Dorsett Trustee → Cynthia S. Tiblier + Bruce V. Tiblier, 0.326 ac Block 22 Tehuacana, $76,000 vendor's lien, LC Vol. 1040 Pg. 510–512, Inst# 00003589, filed 08/25/2000, recorded 08/28/2000; PDF CONFIRMED 2026-03-31)."
        },
        {
          "action": "replace",
          "description": "Mark ISSUE-43 item 15 as PULLED with deed [329] details",
          "find": "  15. LC Vol. 1040 Pg. 510 (Inst# 00003589) — Dorsett Genevieve B Family Trust → Tiblier, deed (08/25/2000) — ISSUE-01",
          "replace_with": "  15. ~~LC Vol. 1040 Pg. 510 (Inst# 00003589)~~ — **PULLED ✓ = deed [329]**; Warranty Deed with Vendor's Lien, Genevieve B. Dorsett Family Trust (Donald J. Dorsett, Trustee) → Cynthia S. Tiblier and husband Bruce V. Tiblier; 0.326 ac Block 22 City of Tehuacana; $10 + $76,000 vendor's lien (Cendant Mortgage); NON-PROJECT PROPERTY — completes Dorsett trust disposition chain ([325] → [329]); all Dorsett LC real property fully accounted for — ISSUE-01 (resolved — independent research value only)"
        }
      ]
    },
    "06_TECHNICAL_SPEC.md": {
      "changed": true,
      "timestamp_summary": "Deed [329] — Dorsett Family Trust post-death warranty deed added to Deed Register (NON-PROJECT PROPERTY; 0.326 ac Block 22 Tehuacana → Tiblier)",
      "operations": [
        {
          "action": "insert_after",
          "description": "Add deed [329] to the Deed Register table after deed [328]",
          "anchor": "| [328] | Lawrence L. Dorsett + Donald J. Dorsett + Diane D. Scripps (affiants) → Public (re: Genevieve B. Dorsett estate heirship) | Limestone | ✓ |",
          "content": "| [329] | Genevieve B. Dorsett Family Trust (Donald J. Dorsett, Trustee) → Cynthia S. Tiblier and husband Bruce V. Tiblier | Limestone | ✓ | LC Vol. 1040, Pg. 510–512, Inst# 00003589, Doc# 003589. Filed Aug 25, 2000 at 4:21 PM; recorded Aug 28, 2000 at 4:00 PM; Sue Lown, County Clerk; Limestone County. | 510–512 (3 pages) | 2000-08-22 | 2000-08-28 | **Warranty Deed with Vendor's Lien** — NON-PROJECT PROPERTY. Genevieve B. Dorsett Family Trust dated December 14, 1992 (Donald J. Dorsett, Trustee, Brazos County TX) conveys 0.326 ac in Block 22, City of Tehuacana, Limestone County to Cynthia S. Tiblier and husband Bruce V. Tiblier (Navarro County TX). Property: same 100×137 ft lot as deed [325]; source deed cross-referenced as \"deed dated February 26, 1993... recorded in Vol. 890, Page 270\" (= deed [325]). Metes-and-bounds description: beginning at found ½\" iron rod at occupied NE corner (SE corner of McCoslin 0.579 ac tract, Vol. 918 Pg. 156 LCDR; NW corner of Robertson 0.434 ac tract, Vol. 1022 Pg. 340 LCDR); S 1°03'57\" W 142.02 ft; N 90°00'00\" W 100.00 ft; N 1°03'57\" W 142.02 ft; N 90°00'00\" E 100.00 ft to POB; containing 0.326 ac. Consideration: $10.00 + $76,000 promissory note (vendor's lien retained; deed of trust to First American Title Insurance Company, Trustee; payee: Cendant Mortgage Corporation). Subject to easements, ROW, prescriptive rights, \"all minerals and royalty reservations and conveyances of record\" (boilerplate — no actual reservation by trust). General warranty. Grantees' mailing address: P.O. Box 191, Tehuacana TX 76686. Acknowledged Aug 22, 2000 before Benjie Reed NP, Limestone County (comm. exp. 9/26/2000). Attorney: Reed & Reed L.L.P., Benjie Reed, P.O. Box 1072, Mexia TX 76667. **Completes Dorsett Family Trust real property disposition chain**: Swint→Garber (1976) → Genevieve (unknown source deed) → Trust ([325], 1993) → Tiblier ([329], 2000). ISSUE-43 item 15. Phase: N/A (non-project property) |"
        }
      ]
    }
  }
}
